code_with_finn/__init__.py
code_with_finn/main.py
code_with_finn/data/bad_error.jpg
code_with_finn/data/error.jpg
code_with_finn/data/keyboard_interrupt.jpg
code_with_finn/data/success.jpg
code_with_finn-1.0.2.dist-info/METADATA
code_with_finn-1.0.2.dist-info/WHEEL
code_with_finn-1.0.2.dist-info/top_level.txt
code_with_finn-1.0.2.dist-info/RECORD
