Metadata-Version: 2.1
Name: code_with_finn
Version: 1.0.2
Summary: Helps feed the soul while coding
Home-page: https://github.com/svank/code_with_finn
Author: Sam Van Kooten
Author-email: vankooten.sam@gmail.com
Project-URL: Bug Tracker, https://github.com/svank/code_with_finn/issues
Classifier: Programming Language :: Python :: 3
Classifier: Operating System :: OS Independent
Requires-Python: >=3.7
Requires-Dist: pillow >=9.0
